README.rst
setup.py
core_helper/__init__.py
core_helper/helper_acces_db.py
core_helper/helper_cache.py
core_helper/helper_classification_model.py
core_helper/helper_clean.py
core_helper/helper_clustering.py
core_helper/helper_dataframe.py
core_helper/helper_feature_selection.py
core_helper/helper_functions.py
core_helper/helper_general.py
core_helper/helper_integracion.py
core_helper/helper_output.py
core_helper/helper_plot.py
core_helper/helper_siagie_kpi.py
core_helper/helper_siagie_kpi_old.py
core_helper/helper_terceros_kpi.py
core_helper/helper_text_mining.py
core_helper/helper_transformers.py
core_helper/test.py
core_helper/test_experimental.py
core_helper/model/__init__.py
core_helper/model/custom_bagging__lgb_model.py
core_helper/model/general.py
core_helper/model/lgb_model.py
core_helper/model/neg_bagging_fraction__lgb_model.py
core_helper/model/scale_pos_weight__lgb_model.py
old/Helper_model_dropout.py
old/__init__.py
old/helper_dropout-Copy1.py
old/helper_dropout-Copy2.py
old/helper_functions_model.py
old/helper_hyper_parametros.py
prj_core.egg-info/PKG-INFO
prj_core.egg-info/SOURCES.txt
prj_core.egg-info/dependency_links.txt
prj_core.egg-info/entry_points.txt
prj_core.egg-info/requires.txt
prj_core.egg-info/top_level.txt