Metadata-Version: 1.1
Name: prj-core
Version: 0.0.46
Summary: prj_core de proyectos de analitica avanzada
Home-page: UNKNOWN
Author: Analitica Avanzada
Author-email: analitica.avanzada.talento@gmail.com
License: NOTFOUND
Download-URL: https://URL_PAQUETE/prj_core/-/archive/master/prj_core-master.tar
Keywords: prj_core,paquete,package
Platform: UNKNOWN
Classifier: Development Status :: 4 - Beta
Classifier: Intended Audience :: Developers
Classifier: Topic :: Software Development :: Build Tools
Classifier: Programming Language :: Python :: 3.7
